[
  {
    "id": "samia-taha-1",
    "data": {
      "gender": "F",
      "first name": "Samia",
      "last name": "Siddiqui",
      "birthday": "22/01/1996",
      "avatar": ""
    },
    "rels": {
      "father": "0",
      "mother": "erum-asif-1",
      "spouses": ["taha-khan-1"]
    }
  },
  {
    "id": "taha-khan-1",
    "data": {
      "gender": "F",
      "first name": "Taha",
      "last name": "Ahmed Khan",
      "birthday": "",
      "avatar": ""
    },
    "rels": {
      "spouses": ["samia-taha-1"],
      "children": ["amin-khan-1"]
    }
  },
  {
    "id": "amin-khan-1",
    "data": {
      "gender": "M",
      "first name": "Amin",
      "last name": "Ahmed Khan",
      "birthday": "",
      "avatar": ""
    },
    "rels": {
      "father": "taha-khan-1",
      "mother": "samia-taha-1"
    }
  }
]
